cli.py
config.py
roll.py
automudae-0.2.0.dist-info/METADATA
automudae-0.2.0.dist-info/WHEEL
automudae-0.2.0.dist-info/entry_points.txt
automudae-0.2.0.dist-info/top_level.txt
automudae-0.2.0.dist-info/RECORD
