Metadata-Version: 2.4
Name: AutoMudae
Version: 0.2.0
Summary: Automate mudae.
Author-email: Rahatul Ghazi <rahatulghazi@gmail.com>
License-Expression: MIT
Project-URL: Homepage, https://github.com/rahaaatul/automudae
Project-URL: Issues, https://github.com/rahaaatul/automudae/issues
Classifier: Programming Language :: Python :: 3
Classifier: Operating System :: OS Independent
Requires-Python: >=3.9
Requires-Dist: discum
Requires-Dist: requests
Requires-Dist: python-dotenv
Requires-Dist: schedule
